[
  {
    "company": "Charlie Health",
    "platform": "greenhouse",
    "slug": "charliehealth"
  },
  {
    "company": "Midi Health",
    "platform": "greenhouse",
    "slug": "midihealth"
  },
  {
    "company": "Frontera Health",
    "platform": "greenhouse",
    "slug": "fronterahealth"
  },
  {
    "company": "Guidelight Health",
    "platform": "greenhouse",
    "slug": "guidelighthealth"
  },
  {
    "company": "Sandstone Care",
    "platform": "greenhouse",
    "slug": "sandstonecare"
  },
  {
    "company": "Kindbridge",
    "platform": "greenhouse",
    "slug": "kindbridgecorporation"
  },
  {
    "company": "Capital Rx (Judi Health)",
    "platform": "greenhouse",
    "slug": "capitalrx"
  },
  {
    "company": "Ceribell",
    "platform": "greenhouse",
    "slug": "ceribell"
  },
  {
    "company": "Vail Health Hospital",
    "platform": "greenhouse",
    "slug": "vailclinicincdbavailhealthhospital"
  },
  {
    "company": "Sideby Care",
    "platform": "greenhouse",
    "slug": "sidebycare"
  },
  {
    "company": "Prosper Health",
    "platform": "greenhouse",
    "slug": "prosperhealth"
  },
  {
    "company": "Cohere Health",
    "platform": "greenhouse",
    "slug": "coherehealth"
  },
  {
    "company": "Spring Health",
    "platform": "greenhouse",
    "slug": "springhealth66"
  },
  {
    "company": "Hone Health",
    "platform": "greenhouse",
    "slug": "honehealth"
  },
  {
    "company": "Modern Health",
    "platform": "greenhouse",
    "slug": "modernhealth"
  },
  {
    "company": "Find HealthCareers",
    "platform": "greenhouse",
    "slug": "find"
  },
  {
    "company": "Pyramid Healthcare",
    "platform": "greenhouse",
    "slug": "1pyra%29mid_health%26care"
  }
]